{
  "id": 100013768717,
  "name": "Fitness Foldable Shoe Bag",
  "url": "https://www.decathlon.com/products/gym-foldable-shoe-bag",
  "vendor": "Domyos",
  "category": "Sport bag",
  "tags": [
    "2",
    "3",
    "5",
    "Artistic Gymnastics",
    "Boy's",
    "CARDIO_FITNESS_ACCESSORIES",
    "CARDIO_FITNESS_BAGS",
    "CODE_R3: 11782",
    "Design Code: 128373",
    "Family: 11782"
  ],
  "images": "https://cdn.shopify.com/s/files/1/1330/6287/products/sac_20a_20chaussure_20kaki_20_7C_20001_20_7C_20PSHOT_20_490180e6-44e4-4340-8e3d-c29eb70c6ac8.jpg?v=1584683232",
  "creation_date": "2020-04-03T15:58:48-07:00",
  "price": "2.49"
}